MANIFEST.in
README.txt
setup.py
docs/HISTORY.txt
docs/LICENSE.txt
src/silva/__init__.py
src/silva.core.views.egg-info/PKG-INFO
src/silva.core.views.egg-info/SOURCES.txt
src/silva.core.views.egg-info/dependency_links.txt
src/silva.core.views.egg-info/namespace_packages.txt
src/silva.core.views.egg-info/not-zip-safe
src/silva.core.views.egg-info/requires.txt
src/silva.core.views.egg-info/top_level.txt
src/silva/core/__init__.py
src/silva/core/views/__init__.py
src/silva/core/views/absoluteurl.py
src/silva/core/views/configure.zcml
src/silva/core/views/ftesting.zcml
src/silva/core/views/httpheaders.py
src/silva/core/views/interfaces.py
src/silva/core/views/language.py
src/silva/core/views/martiansupport.py
src/silva/core/views/site.py
src/silva/core/views/traverser.py
src/silva/core/views/ttwtemplates.py
src/silva/core/views/views.py
src/silva/core/views/templates/service_template.pt
src/silva/core/views/templates/zmi_template.pt
src/silva/core/views/tests/__init__.py
src/silva/core/views/tests/test_absoluteurl.py
src/silva/core/views/tests/test_grok.py
src/silva/core/views/tests/test_head.py
src/silva/core/views/tests/test_site.py
src/silva/core/views/tests/grok/__init__.py
src/silva/core/views/tests/grok/error_cache_headers.py
src/silva/core/views/tests/grok/page_cache_headers.py
src/silva/core/views/tests/grok/view_cache_headers.py