Metadata-Version: 1.1
Name: silva.core.views
Version: 3.0.2
Summary: View rendering for Silva CMS
Home-page: https://github.com/silvacms/silva.core.views
Author: Infrae
Author-email: info@infrae.com
License: BSD
Keywords: silva core views
Platform: UNKNOWN
Classifier: Framework :: Zope2
Classifier: License :: OSI Approved :: BSD License
Classifier: Programming Language :: Python
Classifier: Topic :: Software Development :: Libraries :: Python Modules
